qtpygc/__init__.py
qtpygc-0.1.0.dist-info/METADATA
qtpygc-0.1.0.dist-info/WHEEL
qtpygc-0.1.0.dist-info/top_level.txt
qtpygc-0.1.0.dist-info/RECORD
