Metadata-Version: 2.1
Name: qtpygc
Version: 0.1.0
Summary: Prevent PyQt/PySide crashes due to cross-thread garbage collection
Author-email: Eduard Christian Dumitrescu <eduard.c.dumitrescu@gmail.com>
License: MIT
Requires-Dist: QtPy
Requires-Dist: heapdict
